examples/__init__.py
examples/resumable_upload.py
tests/__init__.py
tests/test_client.py
tests/test_handler.py
tests/test_utils.py
u2s_sdk/__init__.py
u2s_sdk/client.py
u2s_sdk/file.py
u2s_sdk/handler.py
u2s_sdk/utils.py
u2s_sdk-0.3.0.dist-info/LICENSE
u2s_sdk-0.3.0.dist-info/METADATA
u2s_sdk-0.3.0.dist-info/WHEEL
u2s_sdk-0.3.0.dist-info/top_level.txt
u2s_sdk-0.3.0.dist-info/RECORD
